aws_recommendation_a3/__init__.py
aws_recommendation_a3/cloudwatch.py
aws_recommendation_a3/cost_estimations.py
aws_recommendation_a3/dynamodb.py
aws_recommendation_a3/ebs.py
aws_recommendation_a3/ec2.py
aws_recommendation_a3/elb.py
aws_recommendation_a3/kms.py
aws_recommendation_a3/rds.py
aws_recommendation_a3/recommendation.py
aws_recommendation_a3/redshift.py
aws_recommendation_a3/s3.py
aws_recommendation_a3/truted_advisor.py
aws_recommendation_a3/utils.py
aws_recommendation_a3-0.0.15.dist-info/LICENCE
aws_recommendation_a3-0.0.15.dist-info/METADATA
aws_recommendation_a3-0.0.15.dist-info/WHEEL
aws_recommendation_a3-0.0.15.dist-info/top_level.txt
aws_recommendation_a3-0.0.15.dist-info/RECORD
